latex2plos/__init__.py
latex2plos/constants.py
latex2plos/main.py
latex2plos/parser.py
latex2plos/shell.py
latex2plos/utils.py
latex2plos/transformers/__init__.py
latex2plos/transformers/base.py
latex2plos/transformers/copy.py
latex2plos/transformers/include.py
latex2plos-1.0.2.dist-info/DESCRIPTION.rst
latex2plos-1.0.2.dist-info/METADATA
latex2plos-1.0.2.dist-info/RECORD
latex2plos-1.0.2.dist-info/WHEEL
latex2plos-1.0.2.dist-info/entry_points.txt
latex2plos-1.0.2.dist-info/metadata.json
latex2plos-1.0.2.dist-info/top_level.txt
