Metadata-Version: 2.0
Name: latex2plos
Version: 1.0.2
Summary: Console app and Python API for automated preparation of your LaTeX paper for submission in PLOS journals
Home-page: https://github.com/petarmaric/latex2plos
Author: Petar Maric
Author-email: petarmaric@uns.ac.rs
License: BSD
Platform: UNKNOWN
Classifier: Development Status :: 5 - Production/Stable
Classifier: Environment :: Console
Classifier: Intended Audience :: Developers
Classifier: Intended Audience :: Science/Research
Classifier: License :: OSI Approved :: BSD License
Classifier: Operating System :: OS Independent
Classifier: Programming Language :: Python :: 2.7
Classifier: Topic :: Scientific/Engineering
Classifier: Topic :: Text Processing :: Markup :: LaTeX
Classifier: Topic :: Utilities
Provides-Extra: dev
Requires-Dist: friendly-name-mixin (~=1.0)
Requires-Dist: simple-plugins (~=1.0)
Requires-Dist: wand (~=0.5.0)
Provides-Extra: dev
Requires-Dist: pylint (~=1.9); extra == 'dev'
